setup.py
pyvue/__init__.py
pyvue/page.py
pyvue/parser.py
pyvue.egg-info/PKG-INFO
pyvue.egg-info/SOURCES.txt
pyvue.egg-info/dependency_links.txt
pyvue.egg-info/entry_points.txt
pyvue.egg-info/top_level.txt