Metadata-Version: 1.0
Name: pyvue
Version: 0.1.7
Summary: Generate HTML strings in pure python, or JSX style code
Home-page: http://github.com/oakfang/pyvue
Author: Alon Niv
Author-email: oakfang@gmail.com
License: MIT
Platform: UNKNOWN
